dcf/__init__.py
dcf/cashflow.py
dcf/compounding.py
dcf/creditcurve.py
dcf/curve.py
dcf/fx.py
dcf/interestratecurve.py
dcf/interpolation.py
dcf/plans.py
dcf/pricer.py
dcf/ratingclass.py
dcf/volatilitycurve.py
dcf-0.4.dist-info/LICENSE
dcf-0.4.dist-info/METADATA
dcf-0.4.dist-info/WHEEL
dcf-0.4.dist-info/top_level.txt
dcf-0.4.dist-info/RECORD
